hole_fonts/__init__.py
hole_fonts/cli.py
hole_fonts/config.py
hole_fonts/converter.py
hole_fonts/dedup.py
hole_fonts/exporter.py
hole_fonts/metadata.py
hole_fonts/organizer.py
hole_fonts/search.py
hole_fonts/typekit.py
hole_fonts-2.0.1.dist-info/METADATA
hole_fonts-2.0.1.dist-info/WHEEL
hole_fonts-2.0.1.dist-info/entry_points.txt
hole_fonts-2.0.1.dist-info/licenses/LICENSE
hole_fonts-2.0.1.dist-info/RECORD
