Metadata-Version: 2.4
Name: hole-fonts
Version: 2.0.1
Summary: Professional font library management with metadata extraction, search, and format conversion
Project-URL: Homepage, https://github.com/The-HOLE-Foundation/hole-fonts
Project-URL: Documentation, https://github.com/The-HOLE-Foundation/hole-fonts#readme
Project-URL: Repository, https://github.com/The-HOLE-Foundation/hole-fonts
Project-URL: Issues, https://github.com/The-HOLE-Foundation/hole-fonts/issues
Project-URL: Changelog, https://github.com/The-HOLE-Foundation/hole-fonts/blob/main/CHANGELOG.md
Author-email: HOLE Foundation <contact@theholefoundation.org>
License: MIT
License-File: LICENSE
Keywords: font-conversion,font-management,fonts,metadata,otf,ttf,typography,woff2
Classifier: Development Status :: 4 - Beta
Classifier: Intended Audience :: Developers
Classifier: Intended Audience :: End Users/Desktop
Classifier: License :: OSI Approved :: MIT License
Classifier: Operating System :: OS Independent
Classifier: Programming Language :: Python :: 3
Classifier: Programming Language :: Python :: 3.11
Classifier: Programming Language :: Python :: 3.12
Classifier: Programming Language :: Python :: 3.13
Classifier: Programming Language :: Python :: 3.14
Classifier: Topic :: Multimedia :: Graphics :: Graphics Conversion
Classifier: Topic :: Text Processing :: Fonts
Requires-Python: >=3.11
Requires-Dist: click>=8.1.0
Requires-Dist: cu2qu>=1.6.7
Requires-Dist: fonttools[woff]>=4.61.1
Requires-Dist: pyyaml>=6.0
Requires-Dist: requests>=2.31.0
Requires-Dist: rich>=13.0.0
